{
  "title": "NodePools_ListByHcpOpenShiftClusterResource",
  "operationId": "NodePools_ListByHcpOpenShiftClusterResource",
  "parameters": {
    "api-version": "2024-06-10-preview",
    "subscriptionId": "7832CF19-A991-44D3-AC0C-991FD11C4F00",
    "resourceGroupName": "rgopenapi",
    "hcpOpenShiftClusterName": "Replace this value with a string matching RegExp ^[a-zA-Z0-9-]{3,24}$"
  },
  "responses": {
    "200": {
      "body": {
        "value": [
          {
            "properties": {
              "provisioningState": "Succeeded",
              "spec": {
                "version": {
                  "availableUpgrades": [
                    "fradcbrhzzaneuftlyonrqoofu"
                  ]
                },
                "platform": {
                  "subnetId": "eb",
                  "vmSize": "ds",
                  "diskSizeGB": 30,
                  "diskStorageAccountType": "idwoawnxuqbk",
                  "availabilityZone": "pvesjzeivvrnozlyfbwd",
                  "encryptionAtHost": true,
                  "discEncryptionSetId": "uneslgdovxvurupjwncehqlutuwpif",
                  "ephemeralOsDisk": true
                },
                "autoScaling": {
                  "min": 27,
                  "max": 15
                },
                "tuningConfigs": [
                  "wneded"
                ]
              }
            },
            "tags": {
              "key4865": "h"
            },
            "location": "tizpgniwqelquqgnzlhugx",
            "id": "gjsyvwgz",
            "name": "tvbdqkaqlxcj",
            "type": "srwzrpr",
            "systemData": {
              "createdBy": "cfriivusshykeljus",
              "createdByType": "User",
              "createdAt": "2024-03-28T11:00:21.485Z",
              "lastModifiedBy": "rbuvjbcbezqs",
              "lastModifiedByType": "User",
              "lastModifiedAt": "2024-03-28T11:00:21.485Z"
            }
          }
        ],
        "nextLink": "https://microsoft.com/a"
      }
    }
  }
}