{
    "annotations": {
      "list": [
        {
          "builtIn": 1,
          "datasource": {
            "type": "prometheus",
            "uid": "services-usw3jbol"
          },
          "enable": true,
          "hide": true,
          "iconColor": "rgba(0, 211, 255, 1)",
          "name": "Annotations & Alerts",
          "type": "dashboard"
        }
      ]
    },
    "description": "This is a simple dashboard for: https://github.com/banzaicloud/logging-operator utilising Fluent-bit and Fluentd",
    "editable": true,
    "fiscalYearStartMonth": 0,
    "graphTooltip": 0,
    "id": 376,
    "links": [],
    "panels": [
      {
        "collapsed": false,
        "gridPos": {
          "h": 1,
          "w": 24,
          "x": 0,
          "y": 0
        },
        "id": 17,
        "panels": [],
        "title": "fluentbit",
        "type": "row"
      },
      {
        "datasource": {
          "type": "prometheus",
          "uid": "services-usw3jbol"
        },
        "fieldConfig": {
          "defaults": {
            "color": {
              "mode": "palette-classic"
            },
            "custom": {
              "axisBorderShow": false,
              "axisCenteredZero": false,
              "axisColorMode": "text",
              "axisLabel": "",
              "axisPlacement": "auto",
              "barAlignment": 0,
              "barWidthFactor": 0.6,
              "drawStyle": "line",
              "fillOpacity": 10,
              "gradientMode": "none",
              "hideFrom": {
                "legend": false,
                "tooltip": false,
                "viz": false
              },
              "insertNulls": false,
              "lineInterpolation": "linear",
              "lineWidth": 1,
              "pointSize": 5,
              "scaleDistribution": {
                "type": "linear"
              },
              "showPoints": "never",
              "spanNulls": false,
              "stacking": {
                "group": "A",
                "mode": "none"
              },
              "thresholdsStyle": {
                "mode": "off"
              }
            },
            "mappings": [],
            "thresholds": {
              "mode": "absolute",
              "steps": [
                {
                  "color": "green"
                },
                {
                  "color": "red",
                  "value": 80
                }
              ]
            },
            "unit": "bytes"
          },
          "overrides": []
        },
        "gridPos": {
          "h": 6,
          "w": 12,
          "x": 0,
          "y": 1
        },
        "id": 2,
        "options": {
          "dataLinks": [],
          "legend": {
            "calcs": [
              "lastNotNull"
            ],
            "displayMode": "list",
            "placement": "bottom",
            "showLegend": true
          },
          "tooltip": {
            "hideZeros": false,
            "mode": "multi",
            "sort": "none"
          }
        },
        "pluginVersion": "11.6.3",
        "targets": [
          {
            "datasource": {
              "type": "prometheus",
              "uid": "services-usw3jbol"
            },
            "expr": "sum(rate(fluentbit_input_bytes_total{pod=~\"$fluentbit\"}[5m])) by (pod, name)",
            "format": "time_series",
            "hide": false,
            "intervalFactor": 1,
            "legendFormat": "{{ pod }}/{{name}}",
            "refId": "A"
          }
        ],
        "title": "Fluentbit Input Bytes",
        "type": "timeseries"
      },
      {
        "datasource": {
          "type": "prometheus",
          "uid": "services-usw3jbol"
        },
        "fieldConfig": {
          "defaults": {
            "color": {
              "mode": "palette-classic"
            },
            "custom": {
              "axisBorderShow": false,
              "axisCenteredZero": false,
              "axisColorMode": "text",
              "axisLabel": "",
              "axisPlacement": "auto",
              "barAlignment": 0,
              "barWidthFactor": 0.6,
              "drawStyle": "line",
              "fillOpacity": 10,
              "gradientMode": "none",
              "hideFrom": {
                "legend": false,
                "tooltip": false,
                "viz": false
              },
              "insertNulls": false,
              "lineInterpolation": "linear",
              "lineWidth": 1,
              "pointSize": 5,
              "scaleDistribution": {
                "type": "linear"
              },
              "showPoints": "never",
              "spanNulls": false,
              "stacking": {
                "group": "A",
                "mode": "none"
              },
              "thresholdsStyle": {
                "mode": "off"
              }
            },
            "mappings": [],
            "min": 0,
            "thresholds": {
              "mode": "absolute",
              "steps": [
                {
                  "color": "green"
                },
                {
                  "color": "red",
                  "value": 80
                }
              ]
            },
            "unit": "bytes"
          },
          "overrides": []
        },
        "gridPos": {
          "h": 6,
          "w": 12,
          "x": 12,
          "y": 1
        },
        "id": 9,
        "options": {
          "dataLinks": [],
          "legend": {
            "calcs": [
              "lastNotNull"
            ],
            "displayMode": "list",
            "placement": "bottom",
            "showLegend": true
          },
          "tooltip": {
            "hideZeros": false,
            "mode": "multi",
            "sort": "none"
          }
        },
        "pluginVersion": "11.6.3",
        "targets": [
          {
            "datasource": {
              "type": "prometheus",
              "uid": "services-usw3jbol"
            },
            "expr": "sum(rate(fluentbit_output_proc_bytes_total{pod=~\"$fluentbit\"}[5m])) by (pod, name)",
            "format": "time_series",
            "hide": false,
            "intervalFactor": 1,
            "legendFormat": "{{ pod }}/{{name}}",
            "refId": "A"
          }
        ],
        "title": "Fluentbit Output Bytes",
        "type": "timeseries"
      },
      {
        "datasource": {
          "type": "prometheus",
          "uid": "services-usw3jbol"
        },
        "fieldConfig": {
          "defaults": {
            "color": {
              "mode": "palette-classic"
            },
            "custom": {
              "axisBorderShow": false,
              "axisCenteredZero": false,
              "axisColorMode": "text",
              "axisLabel": "",
              "axisPlacement": "auto",
              "barAlignment": 0,
              "barWidthFactor": 0.6,
              "drawStyle": "line",
              "fillOpacity": 10,
              "gradientMode": "none",
              "hideFrom": {
                "legend": false,
                "tooltip": false,
                "viz": false
              },
              "insertNulls": false,
              "lineInterpolation": "linear",
              "lineWidth": 1,
              "pointSize": 5,
              "scaleDistribution": {
                "type": "linear"
              },
              "showPoints": "never",
              "spanNulls": false,
              "stacking": {
                "group": "A",
                "mode": "none"
              },
              "thresholdsStyle": {
                "mode": "off"
              }
            },
            "mappings": [],
            "thresholds": {
              "mode": "absolute",
              "steps": [
                {
                  "color": "green"
                },
                {
                  "color": "red",
                  "value": 80
                }
              ]
            },
            "unit": "cps"
          },
          "overrides": []
        },
        "gridPos": {
          "h": 6,
          "w": 12,
          "x": 0,
          "y": 7
        },
        "id": 40,
        "options": {
          "dataLinks": [],
          "legend": {
            "calcs": [
              "lastNotNull"
            ],
            "displayMode": "list",
            "placement": "bottom",
            "showLegend": true
          },
          "tooltip": {
            "hideZeros": false,
            "mode": "multi",
            "sort": "none"
          }
        },
        "pluginVersion": "11.6.3",
        "targets": [
          {
            "datasource": {
              "type": "prometheus",
              "uid": "services-usw3jbol"
            },
            "expr": "sum(rate(fluentbit_input_records_total{pod=~\"$fluentbit\"}[5m])) by (pod, name)",
            "format": "time_series",
            "hide": false,
            "intervalFactor": 1,
            "legendFormat": "{{ pod }}/{{name}}",
            "refId": "A"
          }
        ],
        "title": "Fluentbit Input Record",
        "type": "timeseries"
      },
      {
        "datasource": {
          "type": "prometheus",
          "uid": "services-usw3jbol"
        },
        "fieldConfig": {
          "defaults": {
            "color": {
              "mode": "palette-classic"
            },
            "custom": {
              "axisBorderShow": false,
              "axisCenteredZero": false,
              "axisColorMode": "text",
              "axisLabel": "",
              "axisPlacement": "auto",
              "barAlignment": 0,
              "barWidthFactor": 0.6,
              "drawStyle": "line",
              "fillOpacity": 10,
              "gradientMode": "none",
              "hideFrom": {
                "legend": false,
                "tooltip": false,
                "viz": false
              },
              "insertNulls": false,
              "lineInterpolation": "linear",
              "lineWidth": 1,
              "pointSize": 5,
              "scaleDistribution": {
                "type": "linear"
              },
              "showPoints": "never",
              "spanNulls": false,
              "stacking": {
                "group": "A",
                "mode": "none"
              },
              "thresholdsStyle": {
                "mode": "off"
              }
            },
            "mappings": [],
            "min": 0,
            "thresholds": {
              "mode": "absolute",
              "steps": [
                {
                  "color": "green"
                },
                {
                  "color": "red",
                  "value": 80
                }
              ]
            },
            "unit": "cps"
          },
          "overrides": []
        },
        "gridPos": {
          "h": 6,
          "w": 12,
          "x": 12,
          "y": 7
        },
        "id": 41,
        "options": {
          "dataLinks": [],
          "legend": {
            "calcs": [
              "lastNotNull"
            ],
            "displayMode": "list",
            "placement": "bottom",
            "showLegend": true
          },
          "tooltip": {
            "hideZeros": false,
            "mode": "multi",
            "sort": "none"
          }
        },
        "pluginVersion": "11.6.3",
        "targets": [
          {
            "datasource": {
              "type": "prometheus",
              "uid": "services-usw3jbol"
            },
            "expr": "sum(rate(fluentbit_output_proc_records_total{pod=~\"$fluentbit\"}[5m])) by (pod, name)",
            "format": "time_series",
            "hide": false,
            "intervalFactor": 1,
            "legendFormat": "{{ pod }}/{{name}}",
            "refId": "A"
          }
        ],
        "title": "Fluentbit Output Records",
        "type": "timeseries"
      },
      {
        "datasource": {
          "type": "prometheus",
          "uid": "services-usw3jbol"
        },
        "fieldConfig": {
          "defaults": {
            "color": {
              "mode": "palette-classic"
            },
            "custom": {
              "axisBorderShow": false,
              "axisCenteredZero": false,
              "axisColorMode": "text",
              "axisLabel": "",
              "axisPlacement": "auto",
              "barAlignment": 0,
              "barWidthFactor": 0.6,
              "drawStyle": "line",
              "fillOpacity": 10,
              "gradientMode": "none",
              "hideFrom": {
                "legend": false,
                "tooltip": false,
                "viz": false
              },
              "insertNulls": false,
              "lineInterpolation": "linear",
              "lineWidth": 1,
              "pointSize": 5,
              "scaleDistribution": {
                "type": "linear"
              },
              "showPoints": "never",
              "spanNulls": false,
              "stacking": {
                "group": "A",
                "mode": "none"
              },
              "thresholdsStyle": {
                "mode": "off"
              }
            },
            "mappings": [],
            "min": 0,
            "thresholds": {
              "mode": "absolute",
              "steps": [
                {
                  "color": "green"
                },
                {
                  "color": "red",
                  "value": 80
                }
              ]
            },
            "unit": "short"
          },
          "overrides": []
        },
        "gridPos": {
          "h": 6,
          "w": 12,
          "x": 0,
          "y": 13
        },
        "id": 11,
        "options": {
          "dataLinks": [],
          "legend": {
            "calcs": [
              "lastNotNull"
            ],
            "displayMode": "list",
            "placement": "bottom",
            "showLegend": true
          },
          "tooltip": {
            "hideZeros": false,
            "mode": "multi",
            "sort": "none"
          }
        },
        "pluginVersion": "11.6.3",
        "targets": [
          {
            "datasource": {
              "type": "prometheus",
              "uid": "services-usw3jbol"
            },
            "expr": "sum(rate(fluentbit_output_retries_total{pod=~\"$fluentbit\"}[1m])) by (pod, name)",
            "format": "time_series",
            "hide": false,
            "intervalFactor": 1,
            "legendFormat": "Retries {{ pod }}/{{name}}",
            "refId": "A"
          },
          {
            "datasource": {
              "type": "prometheus",
              "uid": "services-usw3jbol"
            },
            "expr": "sum(rate(fluentbit_output_retries_failed_total{pod=~\"$fluentbit\"}[1m])) by (pod, name)",
            "format": "time_series",
            "intervalFactor": 1,
            "legendFormat": "Failed {{ pod }}/{{name}}",
            "refId": "B"
          }
        ],
        "title": "Fluentbit Output Retries/Fails",
        "type": "timeseries"
      },
      {
        "datasource": {
          "type": "prometheus",
          "uid": "services-usw3jbol"
        },
        "fieldConfig": {
          "defaults": {
            "color": {
              "mode": "palette-classic"
            },
            "custom": {
              "axisBorderShow": false,
              "axisCenteredZero": false,
              "axisColorMode": "text",
              "axisLabel": "",
              "axisPlacement": "auto",
              "barAlignment": 0,
              "barWidthFactor": 0.6,
              "drawStyle": "line",
              "fillOpacity": 10,
              "gradientMode": "none",
              "hideFrom": {
                "legend": false,
                "tooltip": false,
                "viz": false
              },
              "insertNulls": false,
              "lineInterpolation": "linear",
              "lineWidth": 1,
              "pointSize": 5,
              "scaleDistribution": {
                "type": "linear"
              },
              "showPoints": "never",
              "spanNulls": false,
              "stacking": {
                "group": "A",
                "mode": "none"
              },
              "thresholdsStyle": {
                "mode": "off"
              }
            },
            "mappings": [],
            "min": 0,
            "thresholds": {
              "mode": "absolute",
              "steps": [
                {
                  "color": "green"
                },
                {
                  "color": "red",
                  "value": 80
                }
              ]
            },
            "unit": "bytes"
          },
          "overrides": []
        },
        "gridPos": {
          "h": 6,
          "w": 12,
          "x": 12,
          "y": 13
        },
        "id": 10,
        "options": {
          "dataLinks": [],
          "legend": {
            "calcs": [
              "lastNotNull"
            ],
            "displayMode": "list",
            "placement": "bottom",
            "showLegend": true
          },
          "tooltip": {
            "hideZeros": false,
            "mode": "multi",
            "sort": "none"
          }
        },
        "pluginVersion": "11.6.3",
        "targets": [
          {
            "datasource": {
              "type": "prometheus",
              "uid": "services-usw3jbol"
            },
            "expr": "sum(rate(fluentbit_output_errors_total{pod=~\"$fluentbit\"}[1m])) by (pod, name)",
            "format": "time_series",
            "hide": false,
            "intervalFactor": 1,
            "legendFormat": "{{ pod }}/{{ name }}",
            "refId": "A"
          }
        ],
        "title": "Fluentbit Output Errors",
        "type": "timeseries"
      }
    ],
    "preload": false,
    "refresh": "30s",
    "schemaVersion": 41,
    "tags": [],
    "templating": {
      "list": [
        {
          "current": {
            "text": "Managed_Prometheus_services-usw3jbol",
            "value": "services-usw3jbol"
          },
          "includeAll": false,
          "name": "datasource",
          "options": [],
          "query": "prometheus",
          "refresh": 1,
          "regex": "",
          "type": "datasource"
        },
        {
          "current": {
            "text": [
              "All"
            ],
            "value": [
              "$__all"
            ]
          },
          "datasource": "$datasource",
          "definition": "label_values(fluentbit_input_bytes_total,pod)",
          "includeAll": true,
          "multi": true,
          "name": "fluentbit",
          "options": [],
          "query": "label_values(fluentbit_input_bytes_total,pod)",
          "refresh": 1,
          "regex": "",
          "type": "query"
        }
      ]
    },
    "time": {
      "from": "now-15m",
      "to": "now"
    },
    "timepicker": {},
    "timezone": "",
    "title": "Arobit Forwarder Dashboard",
    "uid": "arobitforwarderudu823uid",
    "version": 2
  }